README
setup.py
multi_pattern_search/__init__.py
multi_pattern_search/keyword2group.py
multi_pattern_search/test.py
multi_pattern_search.egg-info/PKG-INFO
multi_pattern_search.egg-info/SOURCES.txt
multi_pattern_search.egg-info/dependency_links.txt
multi_pattern_search.egg-info/not-zip-safe
multi_pattern_search.egg-info/top_level.txt
multi_pattern_search/cpp/acsmx2.c
multi_pattern_search/cpp/acsmx2.h
multi_pattern_search/cpp/compile.sh
multi_pattern_search/cpp/search.hpp
multi_pattern_search/cpp/search_py.cpp