Metadata-Version: 1.0
Name: multi-pattern-search
Version: 1.2.3
Summary: Multi-Pattern Matching Algorithms 多模式匹配算法
Home-page: UNKNOWN
Author: zsp
Author-email: zsp007@gmail.com
License: UNKNOWN
Platform: UNKNOWN
